nagraj/README.md
nagraj/__init__.py
nagraj/__main__.py
nagraj/cli/__init__.py
nagraj/cli/ascii_art.txt
nagraj/cli/commands/__init__.py
nagraj/cli/commands/init.py
nagraj/cli/main.py
nagraj/config/__init__.py
nagraj/config/schema.py
nagraj/config/settings.py
nagraj/core/__init__.py
nagraj/core/logging.py
nagraj/core/template.py
nagraj/templates/nagraj-full-project-template/cookiecutter.json
nagraj/templates/nagraj-full-project-template/{{cookiecutter.project_name}}/.env.example
nagraj/templates/nagraj-full-project-template/{{cookiecutter.project_name}}/.gitignore
nagraj/templates/nagraj-full-project-template/{{cookiecutter.project_name}}/.nagraj.yaml
nagraj/templates/nagraj-full-project-template/{{cookiecutter.project_name}}/.vscode/settings.json
nagraj/templates/nagraj-full-project-template/{{cookiecutter.project_name}}/README.md
nagraj/templates/nagraj-full-project-template/{{cookiecutter.project_name}}/alembic.ini
nagraj/templates/nagraj-full-project-template/{{cookiecutter.project_name}}/pyproject.toml
nagraj/templates/nagraj-full-project-template/{{cookiecutter.project_name}}/tests/apis/auth_test.hurl
nagraj/templates/nagraj-full-project-template/{{cookiecutter.project_name}}/{{cookiecutter.project_slug}}/__init__.py
nagraj/templates/nagraj-full-project-template/{{cookiecutter.project_name}}/{{cookiecutter.project_slug}}/common/__init__.py
nagraj/templates/nagraj-full-project-template/{{cookiecutter.project_name}}/{{cookiecutter.project_slug}}/common/base/__init__.py
nagraj/templates/nagraj-full-project-template/{{cookiecutter.project_name}}/{{cookiecutter.project_slug}}/common/base/aggregate.py
nagraj/templates/nagraj-full-project-template/{{cookiecutter.project_name}}/{{cookiecutter.project_slug}}/common/base/domain_event.py
nagraj/templates/nagraj-full-project-template/{{cookiecutter.project_name}}/{{cookiecutter.project_slug}}/common/base/domain_service.py
nagraj-0.1.1.dist-info/LICENSE
nagraj-0.1.1.dist-info/METADATA
nagraj-0.1.1.dist-info/WHEEL
nagraj-0.1.1.dist-info/entry_points.txt
nagraj-0.1.1.dist-info/RECORD
