Metadata-Version: 2.3
Name: nagraj
Version: 0.1.1
Summary: A CLI tool for generating DDD/CQRS microservices applications
License: MIT
Keywords: ddd,cqrs,microservices,cli,generator,project-template
Author: Abhishek Pathak
Author-email: writetokumar@gmail.com
Requires-Python: >=3.12,<4.0
Classifier: Development Status :: 3 - Alpha
Classifier: Environment :: Console
Classifier: Intended Audience :: Developers
Classifier: License :: OSI Approved :: MIT License
Classifier: Programming Language :: Python :: 3
Classifier: Programming Language :: Python :: 3.12
Classifier: Programming Language :: Python :: 3.13
Classifier: Topic :: Software Development :: Code Generators
Classifier: Topic :: Software Development :: Libraries :: Python Modules
Requires-Dist: click (>=8.1.8,<9.0.0)
Requires-Dist: cookiecutter (>=2.6.0,<3.0.0)
Requires-Dist: jinja2 (>=3.1.5,<4.0.0)
Requires-Dist: loguru (>=0.7.3,<0.8.0)
Requires-Dist: pydantic (>=2.10.5,<3.0.0)
Requires-Dist: pydantic-settings (>=2.7.1,<3.0.0)
Requires-Dist: pyyaml (>=6.0.2,<7.0.0)
Requires-Dist: rich (>=13.9.4,<14.0.0)
Project-URL: Documentation, https://github.com/krabhishek/nagraj
Project-URL: Homepage, https://github.com/krabhishek/nagraj
Project-URL: Repository, https://github.com/krabhishek/nagraj
